cci_tag_scanner/__init__.py
cci_tag_scanner/conf/__init__.py
cci_tag_scanner/conf/constants.py
cci_tag_scanner/conf/settings.py
cci_tag_scanner/conf/tag_check.conf
cci_tag_scanner/dataset/__init__.py
cci_tag_scanner/dataset/dataset.py
cci_tag_scanner/facets.py
cci_tag_scanner/file_handlers/__init__.py
cci_tag_scanner/file_handlers/base.py
cci_tag_scanner/file_handlers/handler_factory.py
cci_tag_scanner/file_handlers/netcdf.py
cci_tag_scanner/scripts/__init__.py
cci_tag_scanner/scripts/check_json.py
cci_tag_scanner/scripts/check_tags.py
cci_tag_scanner/scripts/command_line_client.py
cci_tag_scanner/scripts/dump_facet_object.py
cci_tag_scanner/tagger.py
cci_tag_scanner/templates/base.html
cci_tag_scanner/templates/ecv.html
cci_tag_scanner/templates/index.html
cci_tag_scanner/tests/conftest.py
cci_tag_scanner/tests/permafrost/ESACCI-PERMAFROST-L4-ALT-ERA5_MODISLST_BIASCORRECTED-AREA4_PP-1997-fv04.0.nc
cci_tag_scanner/tests/permafrost/ESACCI-PERMAFROST-L4-ALT-ERA5_MODISLST_BIASCORRECTED-AREA4_PP-1998-fv04.0.nc
cci_tag_scanner/tests/test_consistency.py
cci_tag_scanner/tests/test_json.py
cci_tag_scanner/tests/test_json_files/example.json
cci_tag_scanner/tests/test_json_files/permafrost.json
cci_tag_scanner/tests/~test_dataset_object.py
cci_tag_scanner/tests/~test_dataset_tree.py
cci_tag_scanner/utils/__init__.py
cci_tag_scanner/utils/dataset_jsons.py
cci_tag_scanner/utils/decorators.py
cci_tag_scanner/utils/elasticsearch.py
cci_tag_scanner/utils/snippets.py
cci_tag_scanner-2.6.0.dist-info/LICENSE
cci_tag_scanner-2.6.0.dist-info/METADATA
cci_tag_scanner-2.6.0.dist-info/WHEEL
cci_tag_scanner-2.6.0.dist-info/entry_points.txt
cci_tag_scanner-2.6.0.dist-info/RECORD
