Metadata-Version: 2.3
Name: cci-tag-scanner
Version: 2.6.0
Summary: This package provides a command line tool moles_esgf_tag to generate dataset tags for both MOLES and ESGF.
License: BSD 3
Author: Daniel Westwood
Author-email: daniel.westwood@stfc.ac.uk
Requires-Python: >=3.9,<4
Classifier: Intended Audience :: Developers
Classifier: License :: OSI Approved :: BSD License
Classifier: Operating System :: OS Independent
Classifier: Programming Language :: Python
Classifier: Programming Language :: Python :: 3
Classifier: Programming Language :: Python :: 3.9
Requires-Dist: ceda-directory-tree (>=1.2.0)
Requires-Dist: elasticsearch (>=8,<9)
Requires-Dist: jinja2 (>=3,<4)
Requires-Dist: netcdf4 (>=1.7.2,<2.0.0)
Requires-Dist: numpy (>=1.25,<2.0)
Requires-Dist: requests (>=2.32.3,<3.0.0)
Requires-Dist: six (>=1.16.0,<2.0.0)
Requires-Dist: tqdm (>=4.45.0,<5)
Requires-Dist: verboselogs (>=1.7)
